README
setup.py
KISSmetrics/__init__.py
pyKISSmetrics.egg-info/PKG-INFO
pyKISSmetrics.egg-info/SOURCES.txt
pyKISSmetrics.egg-info/dependency_links.txt
pyKISSmetrics.egg-info/requires.txt
pyKISSmetrics.egg-info/top_level.txt