Metadata-Version: 1.0
Name: pyKISSmetrics
Version: 1.0.2
Summary: Unofficial Python client for KISSmetrics
Home-page: http://github.com/shakefu/pyKISSmetrics
Author: Jake Alheid
Author-email: jacob.alheid@gmail.com
License: UNKNOWN
Keywords: kissmetrics
Platform: UNKNOWN
Classifier: Programming Language :: Python
Classifier: Operating System :: OS Independent
Classifier: Development Status :: 4 - Beta
Classifier: Intended Audience :: Developers
Classifier: Topic :: Software Development :: Libraries :: Python Modules
